aliyunsdkram/__init__.py
aliyunsdkram/endpoint.py
aliyunsdkram/request/__init__.py
aliyunsdkram/request/v20150501/AddUserToGroupRequest.py
aliyunsdkram/request/v20150501/AttachPolicyToGroupRequest.py
aliyunsdkram/request/v20150501/AttachPolicyToRoleRequest.py
aliyunsdkram/request/v20150501/AttachPolicyToUserRequest.py
aliyunsdkram/request/v20150501/BindMFADeviceRequest.py
aliyunsdkram/request/v20150501/ChangePasswordRequest.py
aliyunsdkram/request/v20150501/ClearAccountAliasRequest.py
aliyunsdkram/request/v20150501/CreateAccessKeyRequest.py
aliyunsdkram/request/v20150501/CreateGroupRequest.py
aliyunsdkram/request/v20150501/CreateLoginProfileRequest.py
aliyunsdkram/request/v20150501/CreatePolicyRequest.py
aliyunsdkram/request/v20150501/CreatePolicyVersionRequest.py
aliyunsdkram/request/v20150501/CreateRoleRequest.py
aliyunsdkram/request/v20150501/CreateUserRequest.py
aliyunsdkram/request/v20150501/CreateVirtualMFADeviceRequest.py
aliyunsdkram/request/v20150501/DecodeDiagnosticMessageRequest.py
aliyunsdkram/request/v20150501/DeleteAccessKeyRequest.py
aliyunsdkram/request/v20150501/DeleteGroupRequest.py
aliyunsdkram/request/v20150501/DeleteLoginProfileRequest.py
aliyunsdkram/request/v20150501/DeletePolicyRequest.py
aliyunsdkram/request/v20150501/DeletePolicyVersionRequest.py
aliyunsdkram/request/v20150501/DeleteRoleRequest.py
aliyunsdkram/request/v20150501/DeleteUserRequest.py
aliyunsdkram/request/v20150501/DeleteVirtualMFADeviceRequest.py
aliyunsdkram/request/v20150501/DetachPolicyFromGroupRequest.py
aliyunsdkram/request/v20150501/DetachPolicyFromRoleRequest.py
aliyunsdkram/request/v20150501/DetachPolicyFromUserRequest.py
aliyunsdkram/request/v20150501/GetAccessKeyLastUsedRequest.py
aliyunsdkram/request/v20150501/GetAccountAliasRequest.py
aliyunsdkram/request/v20150501/GetGroupRequest.py
aliyunsdkram/request/v20150501/GetLoginProfileRequest.py
aliyunsdkram/request/v20150501/GetPasswordPolicyRequest.py
aliyunsdkram/request/v20150501/GetPolicyRequest.py
aliyun_python_sdk_ram-3.3.1.dist-info/LICENSE
aliyun_python_sdk_ram-3.3.1.dist-info/METADATA
aliyun_python_sdk_ram-3.3.1.dist-info/WHEEL
aliyun_python_sdk_ram-3.3.1.dist-info/top_level.txt
aliyun_python_sdk_ram-3.3.1.dist-info/RECORD
